README
setup.py
eav/__init__.py
eav/admin.py
eav/facets.py
eav/fields.py
eav/forms.py
eav/managers.py
eav/models.py
eav/tests.py
eav/widgets.py
eav/locale/ru/LC_MESSAGES/django.mo
eav/locale/ru/LC_MESSAGES/django.po
eav/templates/admin/edit_inline/tabular.html
eav_django.egg-info/PKG-INFO
eav_django.egg-info/SOURCES.txt
eav_django.egg-info/dependency_links.txt
eav_django.egg-info/top_level.txt