Metadata-Version: 1.1
Name: eav-django
Version: 1.4.6
Summary: a reusable Django application which implements the Entity-Attribute-Value data model.
Home-page: http://bitbucket.org/neithere/eav-django/
Author: Andrey Mikhaylenko
Author-email: andy@neithere.net
License: GNU Lesser General Public License (LGPL), Version 3
Download-URL: http://bitbucket.org/neithere/eav-django/get/tip.zip
Keywords: django eav flexible data model object entity attribute value
Platform: UNKNOWN
Classifier: Development Status :: 4 - Beta
Classifier: Environment :: Web Environment
Classifier: Framework :: Django
Classifier: Intended Audience :: Developers
Classifier: License :: OSI Approved :: GNU Library or Lesser General Public License (LGPL)
Classifier: Programming Language :: Python
Classifier: Topic :: Database
Classifier: Topic :: Software Development :: Libraries :: Python Modules
Classifier: Topic :: Text Processing :: General
Requires: python (>= 2.5)
Requires: django (>= 1.1)
Requires: django_autoslug (>= 1.3.9)
Requires: django_view_shortcuts (>= 1.3.5)
Provides: eav
